rnb/__init__.py
rnb/rnbun.py
rnb/data/R37_N3.npz
rnb/utils/__init__.py
rnb/utils/analysis.py
rnb/utils/data_loader.py
rnb/utils/make_figure.py
rnb/utils/tools.py
rnb_wavelet-0.1.3.dist-info/METADATA
rnb_wavelet-0.1.3.dist-info/WHEEL
rnb_wavelet-0.1.3.dist-info/top_level.txt
rnb_wavelet-0.1.3.dist-info/RECORD
