Metadata-Version: 2.1
Name: rnb-wavelet
Version: 0.1.3
Summary: rnb-Wavelet
Home-page: https://github.com/yourusername/rnb
Author: Michael Foti
Author-email: michael-christopher.foti.1@ens.etsmtl.ca
Classifier: Programming Language :: Python :: 3
Classifier: License :: OSI Approved :: MIT License
Classifier: Operating System :: OS Independent
Requires-Python: >=3.6
Requires-Dist: numpy
Requires-Dist: scipy
Requires-Dist: matplotlib
Requires-Dist: statsmodels
